<?xml version="1.0"?>
<stream>
<mp3>
	<name>قصص الانبياء للشيخ الشعراوى</name>
	<url>C_5OTgpRxPk</url>
	<title>PL5FF8AB36613E0548</title>
</mp3>
<mp3>
	<name>تفسير القرآن الكريم  الشيخ عبد الرحمن عبد الخالق</name>
	<url>KpvkUovu7wU</url>
	<title>PLmgmhMYjhVTtTtWyuQceK9bsagKqlCpq_</title>
</mp3>
<mp3>
	<name>قصص القران الكريم الشيخ نبيل العوضي</name>
	<url>ob6l8P1c6qw</url>
	<title>PL9lHPIsZK_SX09wLpvXzMX7t4di8Du2kw</title>
</mp3>
<mp3>
	<name>تفسير جزء عم كاملا للشيخ عائض القرني "التفسير العصري الميسر</name>
	<url>KrCsG9scL44</url>
	<title>PLWiV0jdP3qikJyNwK66gpDfIrUFi68XFv</title>
</mp3>
<mp3>
	<name>قصص الانبياء للشيخ عمر عبد الكافى</name>
	<url>9nNmoctvQss</url>
	<title>PLMA_DTEEZ5srNd1e1BDQKxscGuUeNR1-5</title>
</mp3>
<mp3>
	<name>الإعجاز العلمي في القرآن زغلول النجار (الفضاء)</name>
	<url>WTfVQlnepqQ</url>
	<title>PL_Zg5QrGFm-EfSqU8RTrzZtHT79iR1_5b</title>
</mp3>
<mp3>
	<name>لمسات بيانية في القرآن الكريم - د.فاضل السامرائي</name>
	<url>fKKxUI7b6X0</url>
	<title>PLT41Y2-D8TAFFnia241gl6wWUgPDaNarl</title>
</mp3>
</stream>